ai_companion_py-0.1.5.dist-info/METADATA
ai_companion_py-0.1.5.dist-info/WHEEL
ai_companion_py-0.1.5.dist-info/license_files/LICENSE
ai_companion_py/__init__.py
ai_companion_py/ai_companion_py.pypy39-pp73-x86-linux-gnu.so
ai_companion_py-0.1.5.dist-info/RECORD
